bettermysql/__init__.py
bettermysql-0.0.5.dist-info/LICENSE.txt
bettermysql-0.0.5.dist-info/WHEEL
bettermysql-0.0.5.dist-info/METADATA
bettermysql-0.0.5.dist-info/RECORD
