Metadata-Version: 2.1
Name: bettermysql
Version: 0.0.5
Summary: A simple and lightweight ORM that facilitate some operations on MySQL using of pymysql.
Keywords: better,better mysql,bettermysql
Author: matgasp
Requires-Python: >= 3.9
Classifier: License :: OSI Approved :: MIT License
Classifier: Intended Audience :: Developers
Classifier: Natural Language :: English
Classifier: Development Status :: 5 - Production/Stable
Classifier: Operating System :: Microsoft :: Windows
Classifier: Topic :: Utilities
Classifier: Programming Language :: Python :: 3.9
Classifier: Programming Language :: Python :: 3.10
Classifier: Programming Language :: Python :: 3.11
Classifier: Programming Language :: Python :: 3.12
Requires-Dist: pymysql
Project-URL: Issues, https://github.com/matgasp/bettermysql/issues
Project-URL: Repository, https://github.com/matgasp/bettermysql
